pymanylinuxdemo/__init__.py
pymanylinuxdemo/extension.so
pymanylinuxdemo/.libs/libatlas-dd66cbe8.so.3.0
pymanylinuxdemo/.libs/libcblas-de16e930.so.3.0
pymanylinuxdemo/tests/test_extension.py
pymanylinuxdemo/tests/__init__.py
python_manylinux_demo-1.0.dist-info/RECORD
python_manylinux_demo-1.0.dist-info/WHEEL
python_manylinux_demo-1.0.dist-info/METADATA
python_manylinux_demo-1.0.dist-info/top_level.txt
