Metadata-Version: 2.1
Name: python-manylinux-demo
Version: 1.0
Summary: This is a demo package with a compiled C extension.
Home-page: UNKNOWN
Author: UNKNOWN
Author-email: UNKNOWN
License: UNKNOWN
Platform: UNKNOWN
